[
	{
		"id": 1,
		"name": "Иван Иванов",
		"email": "ivan@example.com",
		"purchases": [
			{ "id": 1, "date": "2025-05-15" },
			{ "id": 2, "date": "2025-05-15" },
			{ "id": 3, "date": "2025-05-20" },
			{ "id": 4, "date": "2025-05-20" },
			{ "id": 6, "date": "2025-05-15" },
			{ "id": 8, "date": "2025-05-15" },
			{ "id": 111, "date": "2025-05-20" },
			{ "id": 34, "date": "2025-05-20" }
		]
	},
	{
		"id": 2,
		"name": "Петр Петров",
		"email": "petr@example.com",
		"purchases": [
			{ "id": 1, "date": "2025-05-15" },
			{ "id": 2, "date": "2025-05-15" },
			{ "id": 3, "date": "2025-05-19" },
			{ "id": 4, "date": "2025-05-22" }
		]
	}
]
